{
  "@microsoft/generator-sharepoint": {
    "solutionName": "mcp365-word",
    "environment": "spo",
    "packageManager": "npm",
    "skipFeatureDeployment": true,
    "isDomainIsolated": false,
    "useGulp": false,
    "componentType": "webpart",
    "template": "react",
    "componentName": "WordExplorer",
    "componentDescription": "MCP365 Explorer: Microsoft Word Server",
    "plusBeta": false,
    "isCreatingSolution": true,
    "version": "1.22.1",
    "libraryName": "mcp365-word",
    "libraryId": "199bfda5-1425-47d9-a73d-22c83ba7bb01"
  }
}
